mkdocs_exporter/__init__.py
mkdocs_exporter/config.py
mkdocs_exporter/formats/__init__.py
mkdocs_exporter/formats/pdf/__init__.py
mkdocs_exporter/formats/pdf/aggregator.py
mkdocs_exporter/formats/pdf/browser.py
mkdocs_exporter/formats/pdf/buttons/__init__.py
mkdocs_exporter/formats/pdf/buttons/download.py
mkdocs_exporter/formats/pdf/config.py
mkdocs_exporter/formats/pdf/plugin.py
mkdocs_exporter/formats/pdf/preprocessor.py
mkdocs_exporter/formats/pdf/renderer.py
mkdocs_exporter/formats/pdf/resources/js/__init__.py
mkdocs_exporter/formats/pdf/resources/js/pagedjs.min.js
mkdocs_exporter/formats/pdf/resources/js/pdf.js
mkdocs_exporter/helpers.py
mkdocs_exporter/logging.py
mkdocs_exporter/page.py
mkdocs_exporter/plugin.py
mkdocs_exporter/preprocessor.py
mkdocs_exporter/renderer.py
mkdocs_exporter/resources/__init__.py
mkdocs_exporter/resources/css/__init__.py
mkdocs_exporter/resources/css/material.css
mkdocs_exporter/resources/css/readthedocs.css
mkdocs_exporter/theme.py
mkdocs_exporter/themes/__init__.py
mkdocs_exporter/themes/factory.py
mkdocs_exporter/themes/material/__init__.py
mkdocs_exporter/themes/material/icons.py
mkdocs_exporter/themes/material/theme.py
mkdocs_exporter/themes/readthedocs/__init__.py
mkdocs_exporter/themes/readthedocs/theme.py
mkdocs_exporter-6.1.1.dist-info/LICENSE
mkdocs_exporter-6.1.1.dist-info/METADATA
mkdocs_exporter-6.1.1.dist-info/WHEEL
mkdocs_exporter-6.1.1.dist-info/entry_points.txt
mkdocs_exporter-6.1.1.dist-info/RECORD
